collective.recipe.plonesite-1.10.0-py3.7-nspkg.pth
collective/recipe/plonesite/__init__.py
collective/recipe/plonesite/plonesite.py
collective.recipe.plonesite-1.10.0.dist-info/METADATA
collective.recipe.plonesite-1.10.0.dist-info/WHEEL
collective.recipe.plonesite-1.10.0.dist-info/entry_points.txt
collective.recipe.plonesite-1.10.0.dist-info/namespace_packages.txt
collective.recipe.plonesite-1.10.0.dist-info/top_level.txt
collective.recipe.plonesite-1.10.0.dist-info/RECORD
