Metadata-Version: 2.1
Name: collective.recipe.plonesite
Version: 1.10.0
Summary: A buildout recipe to create and update a plone site
Home-page: http://sixfeetup.com
Author: Clayton Parker
Author-email: info@sixfeetup.com
License: ZPL
Keywords: plone buildout recipe
Platform: UNKNOWN
Classifier: Framework :: Buildout
Classifier: Intended Audience :: Developers
Classifier: Topic :: Software Development :: Build Tools
Classifier: Topic :: Software Development :: Libraries :: Python Modules
Classifier: License :: OSI Approved :: Zope Public License
Requires-Dist: setuptools
Requires-Dist: zc.buildout
Requires-Dist: six
Provides-Extra: tests
Requires-Dist: zope.testing ; extra == 'tests'
Requires-Dist: zc.buildout ; extra == 'tests'
Provides-Extra: upgrade
Requires-Dist: collective.upgrade (>=1.0rc1) ; extra == 'upgrade'
